.gitignore
CHANGES.txt
README.txt
buildout.cfg
setup.py
collective/__init__.py
collective.hostout.egg-info/PKG-INFO
collective.hostout.egg-info/SOURCES.txt
collective.hostout.egg-info/dependency_links.txt
collective.hostout.egg-info/entry_points.txt
collective.hostout.egg-info/namespace_packages.txt
collective.hostout.egg-info/not-zip-safe
collective.hostout.egg-info/requires.txt
collective.hostout.egg-info/top_level.txt
collective/hostout/README.txt
collective/hostout/__init__.py
collective/hostout/fabfile.py
collective/hostout/hostout.py
collective/hostout/tests.py
collective/hostout/datafs/__init__.py
collective/hostout/datafs/fabfile.py
collective/hostout/mrdeveloper/__init__.py
collective/hostout/mrdeveloper/fabfile.py
collective/hostout/supervisor/__init__.py
collective/hostout/supervisor/fabfile.py
collective/hostout/ubuntu/__init__.py
collective/hostout/ubuntu/fabfile.py
collective/hostout/ubuntu/newScripts/README
collective/hostout/ubuntu/newScripts/build_python.simple.sh
collective/hostout/ubuntu/newScripts/install.sh
collective/hostout/ubuntu/newScripts/test.sh
collective/hostout/ubuntu/newScripts/helper_scripts/build_libjpeg.sh
collective/hostout/ubuntu/newScripts/helper_scripts/build_python.sh
collective/hostout/ubuntu/newScripts/helper_scripts/build_readline.sh
collective/hostout/ubuntu/newScripts/helper_scripts/build_zlib.sh
collective/hostout/ubuntu/newScripts/helper_scripts/checkLibs.sh