Metadata-Version: 1.0
Name: collective.hostout
Version: 0.9.3
Summary: one click deployment for buildout based applications
Home-page: https://svn.plone.org/svn/collective/collective.hostout
Author: Dylan Jay
Author-email: software@pretaweb.com
License: GPL
Keywords: buildout,deploy,deployment,server,plone,django,host,hosting
Platform: UNKNOWN
